x_lolo/__init__.py
x_lolo/cookie.py
x_lolo/followers_list_pagination.py
x_lolo/media.py
x_lolo/post.py
x_lolo/post_pagination.py
x_lolo/request_payload_and_headers.py
x_lolo/session.py
x_lolo/user.py
x_lolo/utils/__init__.py
x_lolo/utils/all.py
x_lolo/utils/auth_flows.py
x_lolo/utils/get_guest_ids.py
x_lolo-0.1.18.dist-info/LICENSE
x_lolo-0.1.18.dist-info/METADATA
x_lolo-0.1.18.dist-info/WHEEL
x_lolo-0.1.18.dist-info/top_level.txt
x_lolo-0.1.18.dist-info/RECORD
