Metadata-Version: 2.1
Name: x_lolo
Version: 0.1.18
Summary: A Python library for direct interaction with Twitter's unofficial API
Home-page: https://github.com/mohaskii/x_lolo_project
Author: lolo skiiii
Author-email: uha22211@gmail.com
Classifier: Programming Language :: Python :: 3
Classifier: License :: OSI Approved :: MIT License
Classifier: Operating System :: OS Independent
Classifier: Topic :: Internet :: WWW/HTTP :: Dynamic Content
Classifier: Topic :: Software Development :: Libraries :: Python Modules
Classifier: Topic :: Internet :: WWW/HTTP :: Browsers
Classifier: Topic :: Software Development :: Libraries :: Application Frameworks
Classifier: Topic :: Internet :: WWW/HTTP :: Indexing/Search
Classifier: Topic :: Internet
Classifier: Intended Audience :: Developers
Classifier: Development Status :: 4 - Beta
Classifier: Natural Language :: English
Requires-Python: >=3.6
License-File: LICENSE
Requires-Dist: requests
Requires-Dist: bs4
Requires-Dist: brotli
Requires-Dist: zstandard
Requires-Dist: PyYAML
